{"in_reply_to_status_id_str":null,"in_reply_to_status_id":null,"possibly_sensitive":false,"coordinates":null,"created_at":"Fri Jun 12 14:19:04 +0000 2015","truncated":false,"in_reply_to_user_id_str":null,"source":"<a href=\"http://www.socialflow.com\" rel=\"nofollow\">SocialFlow<\/a>","retweet_count":5,"retweeted":false,"geo":null,"in_reply_to_screen_name":null,"is_quote_status":false,"entities":{"urls":[{"display_url":"trib.al/AQOvOMk","indices":[59,81],"expanded_url":"http://trib.al/AQOvOMk","url":"http://t.co/ePg5r8kSPW"}],"hashtags":[],"user_mentions":[],"symbols":[]},"id_str":"609364298847141889","in_reply_to_user_id":null,"favorite_count":6,"id":609364298847141889,"text":"The ultimate Moscow quiz \u2013 have you been paying attention? http://t.co/ePg5r8kSPW","place":null,"contributors":null,"lang":"en","user":{"utc_offset":3600,"friends_count":1095,"profile_image_url_https":"https://pbs.twimg.com/profile_images/564829693736546305/8o1OPz2e_normal.png","listed_count":39294,"profile_background_image_url":"http://pbs.twimg.com/profile_background_images/704160749/ff996aa3bc2009a2f9b97cdd43e8b5b7.png","default_profile_image":false,"favourites_count":130,"description":"Top stories, special features, live blogs and more","created_at":"Thu Nov 05 23:49:19 +0000 2009","is_translator":false,"profile_background_image_url_https":"https://pbs.twimg.com/profile_background_images/704160749/ff996aa3bc2009a2f9b97cdd43e8b5b7.png","protected":false,"screen_name":"guardian","id_str":"87818409","profile_link_color":"005789","is_translation_enabled":true,"id":87818409,"geo_enabled":false,"profile_background_color":"FFFFFF","lang":"en","profile_sidebar_border_color":"FFFFFF","profile_text_color":"333333","verified":true,"profile_image_url":"http://pbs.twimg.com/profile_images/564829693736546305/8o1OPz2e_normal.png","time_zone":"London","url":"http://t.co/rrGq778cPt","contributors_enabled":false,"profile_background_tile":false,"profile_banner_url":"https://pbs.twimg.com/profile_banners/87818409/1427295976","entities":{"description":{"urls":[]},"url":{"urls":[{"display_url":"theguardian.com","indices":[0,22],"expanded_url":"http://theguardian.com","url":"http://t.co/rrGq778cPt"}]}},"statuses_count":155894,"follow_request_sent":false,"followers_count":3745014,"profile_use_background_image":false,"default_profile":false,"following":false,"name":"The Guardian ","location":"London","profile_sidebar_fill_color":"CAE3F3","notifications":false},"favorited":false}